LICENSE
MANIFEST.in
README.rst
setup.py
sprockets/__init__.py
sprockets/cli.py
sprockets.egg-info/PKG-INFO
sprockets.egg-info/SOURCES.txt
sprockets.egg-info/dependency_links.txt
sprockets.egg-info/entry_points.txt
sprockets.egg-info/namespace_packages.txt
sprockets.egg-info/not-zip-safe
sprockets.egg-info/top_level.txt