Metadata-Version: 1.1
Name: sprockets
Version: 0.1.1
Summary: A modular, loosely coupled micro-framework built on top of Tornado simplifying the creation of web applications and RabbitMQ workers
Home-page: https://github.com/sprockets/sprockets
Author: AWeber Communications
Author-email: UNKNOWN
License: Copyright (c) 2014 AWeber Communications
